sectools/__init__.py
sectools/data/__init__.py
sectools/data/regex.py
sectools/fileformats/Markdown.py
sectools/fileformats/__init__.py
sectools/network/__init__.py
sectools/network/domains.py
sectools/network/ip.py
sectools/web/__init__.py
sectools/windows/__init__.py
sectools/windows/crypto.py
sectools/windows/ldap/ldap.py
sectools/windows/ldap/wrappers.py
sectools-1.5.1.dist-info/licenses/LICENSE
sectools-1.5.1.dist-info/METADATA
sectools-1.5.1.dist-info/WHEEL
sectools-1.5.1.dist-info/top_level.txt
sectools-1.5.1.dist-info/RECORD
