Metadata-Version: 2.4
Name: sectools
Version: 1.5.1
Summary: A python library containing the base functions for security tools
Home-page: https://github.com/p0dalirius/sectools
Author: Podalirius
Author-email: Podalirius <podalirius@protonmail.com>
License: MIT
Requires-Python: >=3.11
License-File: LICENSE
Dynamic: author
Dynamic: home-page
Dynamic: license-file
Dynamic: requires-python
